smoothcon/__about__.py
smoothcon/__init__.py
smoothcon/smoothcon.py
smoothcon-0.0.9.dist-info/METADATA
smoothcon-0.0.9.dist-info/WHEEL
smoothcon-0.0.9.dist-info/licenses/LICENSE
smoothcon-0.0.9.dist-info/RECORD
