Metadata-Version: 2.4
Name: smoothcon
Version: 0.0.9
Summary: Get basis and penalty matrices from mgcv and convert them to numpy arrays
Author: Johannes Brachem
License-File: LICENSE
Keywords: machine-learning,statistics
Classifier: Intended Audience :: Science/Research
Classifier: License :: OSI Approved :: MIT License
Classifier: Programming Language :: Python :: 3
Classifier: Programming Language :: Python :: 3.13
Requires-Python: <3.14,>=3.13
Requires-Dist: numpy>=2.2.5
Requires-Dist: pandas>=2.2.3
Requires-Dist: polars>=1.31.0
Requires-Dist: ryp>=0.2.0
